openlifu/__init__.py
openlifu/_version.py
openlifu/_version.pyi
openlifu/geo.py
openlifu/py.typed
openlifu/virtual_fit.py
openlifu/bf/__init__.py
openlifu/bf/pulse.py
openlifu/bf/sequence.py
openlifu/bf/apod_methods/__init__.py
openlifu/bf/apod_methods/apodmethod.py
openlifu/bf/apod_methods/maxangle.py
openlifu/bf/apod_methods/piecewiselinear.py
openlifu/bf/apod_methods/uniform.py
openlifu/bf/delay_methods/__init__.py
openlifu/bf/delay_methods/delaymethod.py
openlifu/bf/delay_methods/direct.py
openlifu/bf/focal_patterns/__init__.py
openlifu/bf/focal_patterns/focal_pattern.py
openlifu/bf/focal_patterns/single.py
openlifu/bf/focal_patterns/wheel.py
openlifu/db/__init__.py
openlifu/db/database.py
openlifu/db/session.py
openlifu/db/subject.py
openlifu/db/user.py
openlifu/io/LIFUConfig.py
openlifu/io/LIFUHVController.py
openlifu/io/LIFUInterface.py
openlifu/io/LIFUSignal.py
openlifu/io/LIFUTXDevice.py
openlifu/io/LIFUUart.py
openlifu/io/__init__.py
openlifu/nav/__init__.py
openlifu/nav/photoscan.py
openlifu/nav/meshroom_pipelines/__init__.py
openlifu/nav/meshroom_pipelines/default_pipeline.mg
openlifu/nav/meshroom_pipelines/downsample_1x_pipeline.mg
openlifu/nav/meshroom_pipelines/downsample_4x_pipeline.mg
openlifu/nav/meshroom_pipelines/downsample_8x_pipeline.mg
openlifu/nav/meshroom_pipelines/draft_pipeline.mg
openlifu/nav/modnet_checkpoints/__init__.py
openlifu/plan/__init__.py
openlifu/plan/param_constraint.py
openlifu/plan/protocol.py
openlifu/plan/run.py
openlifu/plan/solution.py
openlifu/plan/solution_analysis.py
openlifu/plan/target_constraints.py
openlifu/seg/__init__.py
openlifu/seg/material.py
openlifu/seg/seg_method.py
openlifu/seg/skinseg.py
openlifu/seg/seg_methods/__init__.py
openlifu/seg/seg_methods/uniform.py
openlifu/sim/__init__.py
openlifu/sim/kwave_if.py
openlifu/sim/sim_setup.py
openlifu/util/annotations.py
openlifu/util/assets.py
openlifu/util/checkgpu.py
openlifu/util/dict_conversion.py
openlifu/util/json.py
openlifu/util/strings.py
openlifu-0.15.0.dist-info/METADATA
openlifu-0.15.0.dist-info/WHEEL
openlifu-0.15.0.dist-info/licenses/LICENSE
openlifu-0.15.0.dist-info/RECORD
