Metadata-Version: 2.4
Name: openlifu
Version: 0.15.0
Summary: Openwater Focused Ultrasound Toolkit
Project-URL: Homepage, https://github.com/OpenwaterHealth/OpenLIFU-python
Project-URL: Bug Tracker, https://github.com/OpenwaterHealth/OpenLIFU-python/issues
Project-URL: Discussions, https://github.com/OpenwaterHealth/OpenLIFU-python/discussions
Project-URL: Changelog, https://github.com/OpenwaterHealth/OpenLIFU-python/releases
Author-email: Peter Hollender <peterhollender@gmail.com>
License: # GNU AFFERO GENERAL PUBLIC LICENSE
License-File: LICENSE
Classifier: Development Status :: 1 - Planning
Classifier: Intended Audience :: Developers
Classifier: Intended Audience :: Science/Research
Classifier: License :: OSI Approved :: MIT License
Classifier: Operating System :: OS Independent
Classifier: Programming Language :: Python
Classifier: Programming Language :: Python :: 3
Classifier: Programming Language :: Python :: 3 :: Only
Classifier: Programming Language :: Python :: 3.10
Classifier: Programming Language :: Python :: 3.11
Classifier: Programming Language :: Python :: 3.12
Classifier: Topic :: Scientific/Engineering
Classifier: Typing :: Typed
Requires-Python: >=3.10
Requires-Dist: crc
Requires-Dist: crcmod
Requires-Dist: embreex; platform_machine == 'x86_64' or platform_machine == 'AMD64'
Requires-Dist: h5py
Requires-Dist: ipykernel
Requires-Dist: k-wave-python==0.4.0
Requires-Dist: matplotlib
Requires-Dist: nibabel
Requires-Dist: numpy<2
Requires-Dist: nvidia-ml-py
Requires-Dist: onnxruntime==1.18.0
Requires-Dist: opencv-contrib-python
Requires-Dist: openexr
Requires-Dist: pandas
Requires-Dist: pydicom
Requires-Dist: pyserial
Requires-Dist: scikit-image
Requires-Dist: scipy
Requires-Dist: sphinx
Requires-Dist: trimesh
Requires-Dist: vtk
Requires-Dist: xarray[io]
Provides-Extra: dev
Requires-Dist: dvc[gdrive]; extra == 'dev'
Requires-Dist: pytest-cov>=3; extra == 'dev'
Requires-Dist: pytest-mock; extra == 'dev'
Requires-Dist: pytest>=6; extra == 'dev'
Provides-Extra: docs
Requires-Dist: furo>=2023.08.17; extra == 'docs'
Requires-Dist: myst-parser>=0.13; extra == 'docs'
Requires-Dist: sphinx-autodoc-typehints; extra == 'docs'
Requires-Dist: sphinx-copybutton; extra == 'docs'
Requires-Dist: sphinx>=7.0; extra == 'docs'
Provides-Extra: test
Requires-Dist: pytest-cov>=3; extra == 'test'
Requires-Dist: pytest-mock; extra == 'test'
Requires-Dist: pytest>=6; extra == 'test'
